cordra/__init__.py
cordra/cordraClient.py
cordra/cordraMethods.py
cordra/cordraObject.py
cordra/dataset.py
cordra/utils.py
CordraPy_RDF-0.4.2.dist-info/LICENSE.md
CordraPy_RDF-0.4.2.dist-info/METADATA
CordraPy_RDF-0.4.2.dist-info/WHEEL
CordraPy_RDF-0.4.2.dist-info/top_level.txt
CordraPy_RDF-0.4.2.dist-info/RECORD
