Metadata-Version: 2.1
Name: CordraPy-RDF
Version: 0.4.2
Summary: Python client interface to a cordra instance
Home-page: UNKNOWN
Author: Zachary Trautt, Faical Yannick Congo, Sven Voigt
Author-email: svenpvoigt@gmail.com
License: UNKNOWN
Platform: UNKNOWN
License-File: LICENSE.md
Requires-Dist: requests
Requires-Dist: pandas
Requires-Dist: fastjsonschema
Requires-Dist: lucene-querybuilder
